damiao.py
python_can_damiao-0.1.0.dist-info/licenses/LICENSE
python_can_damiao-0.1.0.dist-info/METADATA
python_can_damiao-0.1.0.dist-info/WHEEL
python_can_damiao-0.1.0.dist-info/entry_points.txt
python_can_damiao-0.1.0.dist-info/top_level.txt
python_can_damiao-0.1.0.dist-info/RECORD
