Metadata-Version: 2.4
Name: python-can-damiao
Version: 0.1.0
Summary: Python-can Damiao USB-CAN adapter plugin
Author-email: Yichuan Gao <i@gycis.me>
License: Copyright (c) 2025 gaoyichuan
Project-URL: Homepage, https://github.com/gaoyichuan/python-can-damiao
Project-URL: Documentation, https://gitee.com/kit-miao/dm-tools/tree/master/USB%E8%BD%ACCAN
Keywords: can,damiao,usb-can
Requires-Python: >=3.9
License-File: LICENSE
Requires-Dist: python-can>=4.0.0
Requires-Dist: pyserial>=3.5
Dynamic: license-file
